README.rst
setup.py
main/orangecloud_client/__init__.py
main/orangecloud_client/abstract_domain.py
main/orangecloud_client/api.py
main/orangecloud_client/error_handling.py
main/orangecloud_client/files.py
main/orangecloud_client/folders.py
main/orangecloud_client/freespace.py
main/orangecloud_client/commands/__init__.py
main/orangecloud_client/commands/command_client.py
main/orangecloud_client/commands/main.py
main/orangecloud_client/commands/shell/__init__.py
main/orangecloud_client/commands/shell/commands.py
main/orangecloud_client/commands/shell/parser.py
orangecloud_client.egg-info/PKG-INFO
orangecloud_client.egg-info/SOURCES.txt
orangecloud_client.egg-info/dependency_links.txt
orangecloud_client.egg-info/entry_points.txt
orangecloud_client.egg-info/not-zip-safe
orangecloud_client.egg-info/requires.txt
orangecloud_client.egg-info/top_level.txt